finsolvepy/__init__.py
finsolvepy/calculation.py
finsolvepy/information.py
finsolvepy/database/__init__.py
finsolvepy/database/apis.py
finsolvepy/database/company_symbol_dict.py
finsolvepy/database/complete_data.csv
finsolvepy/database/indices_descriptions.csv
finsolvepy-2.0.0.dist-info/licenses/LICENSE
finsolvepy-2.0.0.dist-info/METADATA
finsolvepy-2.0.0.dist-info/WHEEL
finsolvepy-2.0.0.dist-info/top_level.txt
finsolvepy-2.0.0.dist-info/RECORD
