Metadata-Version: 2.4
Name: finsolvepy
Version: 2.0.0
Summary: finsolvepy is a Python package for comprehensive financial analysis, enabling users to access detailed stock and cryptocurrency data, validate market symbols, convert currencies, and perform key financial calculations with ease.
Home-page: https://github.com/vengateshk18/finsolvepy
Author: Vengatesh K
Author-email: vengatesh00014@example.com
Classifier: Programming Language :: Python :: 3
Classifier: Programming Language :: Python :: 3.7
Classifier: Programming Language :: Python :: 3.8
Classifier: Programming Language :: Python :: 3.9
Classifier: Programming Language :: Python :: 3.10
Classifier: Programming Language :: Python :: 3.11
Classifier: License :: OSI Approved :: MIT License
Classifier: Operating System :: OS Independent
Requires-Python: >=3.7,<4.0
License-File: LICENSE
Requires-Dist: pandas<3.0.0,>=1.0.0
Requires-Dist: requests<3.0.0,>=2.0.0
Requires-Dist: python-dotenv>=0.10.2
Dynamic: author
Dynamic: author-email
Dynamic: classifier
Dynamic: description
Dynamic: description-content-type
Dynamic: home-page
Dynamic: license-file
Dynamic: requires-dist
Dynamic: requires-python
Dynamic: summary
